{
    "Version": "33.1.3.13",
    "Shield": "0xE7ED528",
    "UWorld": "0x10203478",
    "GNames": "0x10466B58",
    "GNamesOffset2": "0x8",
    "Level": "0x150",
    "Actor": "0xB8",
    "GameInstance": "0x160",
    "LocalPlayer": "0x60",
    "PlayerController": "0x30",
    "AcknowledgedPawn": "0x4B8",
    "PlayerCameraManager": "0x4E0",
    "IsRor": "0x0",
    "DecryptOne": "0x33E4D753",
    "DecryptTwo": "0xFE4C1A1E",
    "TableOne": "0x7",
    "TableTwo": "0x10",
    "ObjectId": "0x10",
    "ChunkSize": "0x3FD0",
    "PlayerState": "0x440",
    "Audience": "0xFF8",
    "PlayerName": "0x468",
    "PlayerStatistic": "0x8C0",
    "TeamNumber": "0x1740",
    "SurvivalLevel": "0xBAC",
    "Position": "0x350",
    "Eyes": "0x74C",
    "BoneArray": "0xAC8",
    "ComponentToWorld": "0x340",
    "bAlwaysCreatePhysicsState": "0x488",
    "Mesh": "0x4F0",
    "HealthFlag": "0x308",
    "Health1": "0xA40",
    "Health2": "0xA30",
    "Health3": "0xA5C",
    "Health4": "0xA48",
    "IsHealthEncryption": "0xA5D",
    "DecryptHealthValue": "0xA58",
    "GroggyHealth": "0x1500",
    "XorKeys": [
        "0xCEC7A59E",
        "0x9B63B221",
        "0xCA1945A5",
        "0x21384881",
        "0x06911D0A",
        "0x23DDAC03",
        "0x094581C8",
        "0xA521B721",
        "0x0BAC7A58",
        "0xB0EF2187",
        "0xE27534B7",
        "0x878ADB1A",
        "0xBD06E4D5",
        "0x21938107",
        "0x81099E38",
        "0xE3D62AFB"
    ],
    "CameraPos": "0x1768",
    "CameraRot": "0x175C",
    "CameraFov": "0x1CF0",
    "Orientation": "0x1B4C",
    "MapJudge": "0x700",
    "WorldToMiniMap": "0x9B4",
    "WidgetStateMap": "0x560",
    "BlockInputWidgetList": "0x5D8",
    "MyHUD": "0x4D8",
    "Visibility": "0xA1",
    "Slot": "0x30",
    "LayoutData": "0x38",
    "Offsets": "0x0",
    "Alignment": "0x20",
    "TrainingMapGrid": "5D8",
    "MapGrid": "0x498",
    "SelectMinimapSizeIndex": "0x5C0",
    "AnimScriptInstance": "0xE10",
    "ControlRotation_CP": "0xCA0",
    "RecoilADSRotation_CP": "0x91C",
    "bIsScoping": "0xC16",
    "Stance_CP": "0x613",
    "WeaponProcessor": "0xA38",
    "CurrentWeaponIndex": "0x301",
    "EquippedWeapons": "0x1F8",
    "AttachedItems": "0x828",
    "WeaponAttachmentData": "0x138",
    "ItemID": "0x268"
}