{
    "Version": "36.1.1.47",
    "Shield": "0xE871B28",
    "UWorld": "0x101F1E88",
    "GNames": "0x104768E8",
    "GNamesOffset2": "0x10",
    "Level": "0x8F0",
    "Actor": "0x1B8",
    "GameInstance": "0x2C8",
    "LocalPlayer": "0x30",
    "PlayerController": "0x30",
    "AcknowledgedPawn": "0x4A8",
    "PlayerCameraManager": "0x4D0",
    "IsRor": "0x0",
    "DecryptOne": "0x123E0A89",
    "DecryptTwo": "0x18B70A89",
    "TableOne": "0x9",
    "TableTwo": "0x10",
    "ObjectId": "0x1C",
    "ChunkSize": "0x4060",
    "PlayerState": "0x428",
    "Audience": "0x1100",
    "PlayerName": "0x1070",
    "PlayerStatistic": "0x4CC",
    "TeamNumber": "0xFF8",
    "SquadMemberIndex": "0x508",
    "SurvivalLevel": "0xBA4",
    "Position": "0x280",
    "Eyes": "0x74C",
    "BoneArray": "0xAD8",
    "ComponentToWorld": "0x270",
    "bAlwaysCreatePhysicsState": "0x488",
    "RootComponent": "0x1E0",
    "ComponentVelocity": "0x334",
    "VehicleRiderComponent": "0x1F50",
    "SeatIndex": "0x220",
    "LastVehiclePawn": "0x260",
    "ReplicatedMovement": "0x70",
    "Mesh": "0x638",
    "HealthFlag": "0x28",
    "Health1": "0x950",
    "Health2": "0x9B8",
    "Health3": "0x974",
    "Health4": "0x960",
    "IsHealthEncryption": "0x975",
    "DecryptHealthValue": "0x970",
    "GroggyHealth": "0x15C0",
    "XorKeys": [
        "0xCEC7A59B",
        "0x9B63B2A9",
        "0xCA3DCDA5",
        "0xA93848A5",
        "0x22911D0A",
        "0x23DDA98B",
        "0x945A5C8",
        "0xA521B221",
        "0xBA97A58",
        "0xB0EFA987",
        "0xE275BCB2",
        "0x878ADB3E",
        "0xBD226CD5",
        "0xA993A507",
        "0xA5099E38",
        "0xE6D32A73"
    ],
    "CameraPos": "0xFDC",
    "CameraRot": "0xFD0",
    "CameraFov": "0xFC4",
    "Orientation": "0x199C",
    "MapJudge": "0x6F0",
    "WorldToMiniMap": "0x34C",
    "WidgetStateMap": "0x548",
    "BlockInputWidgetList": "0x5C0",
    "MyHUD": "0x4C8",
    "Visibility": "0xA1",
    "Slot": "0x30",
    "LayoutData": "0x38",
    "Offsets": "0x0",
    "Alignment": "0x20",
    "TrainingMapGrid": "0x5E0",
    "MapGrid": "0x4A8",
    "SelectMinimapSizeIndex": "0x5B8",
    "AnimScriptInstance": "0xE20",
    "ControlRotation_CP": "0x714",
    "RecoilADSRotation_CP": "0x8E4",
    "bIsScoping": "0x91D",
    "Stance_CP": "0x5C0",
    "WeaponProcessor": "0x988",
    "CurrentWeaponIndex": "0x309",
    "EquippedWeapons": "0x1F8",
    "AttachedItems": "0x868",
    "WeaponAttachmentData": "0x128",
    "WeaponTrajectoryData": "0x11E8",
    "TrajectoryConfig": "0x100",
    "ItemID": "0x26C",
    "Physx_sdk": "0xFD1EE48"
}